src/chunker.py
src/config.py
src/embedding.py
src/loader.py
src/model_loader.py
src/prompts.py
src/qa_chain.py
src/utils.py
src/vectorstore.py
universal_offline_ai_chatbot-0.1.0.dist-info/licenses/LICENSE
universal_offline_ai_chatbot-0.1.0.dist-info/METADATA
universal_offline_ai_chatbot-0.1.0.dist-info/WHEEL
universal_offline_ai_chatbot-0.1.0.dist-info/entry_points.txt
universal_offline_ai_chatbot-0.1.0.dist-info/top_level.txt
universal_offline_ai_chatbot-0.1.0.dist-info/RECORD
