Metadata-Version: 2.4
Name: universal-offline-ai-chatbot
Version: 0.1.0
Summary: Universal Offline AI Chatbot powered by local Mistral + FAISS + LangChain
Home-page: https://github.com/AdityaBhatt3010/Universal-Offline-AI-Chatbot
Author: Aditya Bhatt
Author-email: info.adityabhatt3010@gmail.com
License: MIT
Classifier: Programming Language :: Python :: 3
Classifier: License :: OSI Approved :: MIT License
Classifier: Operating System :: OS Independent
Requires-Python: >=3.8
License-File: LICENSE
Requires-Dist: streamlit>=1.33.0
Requires-Dist: langchain>=0.2.0
Requires-Dist: langchain-community>=0.2.0
Requires-Dist: langchain-core>=0.2.0
Requires-Dist: langchainhub>=0.1.15
Requires-Dist: sentence-transformers>=2.2.2
Requires-Dist: faiss-cpu>=1.7.4
Requires-Dist: pypdf>=3.9.1
Requires-Dist: python-dotenv>=1.0.1
Requires-Dist: pyfiglet>=1.0.2
Requires-Dist: termcolor>=2.3.0
Requires-Dist: rich>=13.7.0
Dynamic: author
Dynamic: author-email
Dynamic: classifier
Dynamic: description
Dynamic: description-content-type
Dynamic: home-page
Dynamic: license
Dynamic: license-file
Dynamic: requires-dist
Dynamic: requires-python
Dynamic: summary
